photos_time_warp/__init__.py
photos_time_warp/__main__.py
photos_time_warp/_version.py
photos_time_warp/cli.py
photos_time_warp/compare_exif.py
photos_time_warp/datetime_utils.py
photos_time_warp/exif_updater.py
photos_time_warp/photosalbum.py
photos_time_warp/phototz.py
photos_time_warp/sqlite_native.py
photos_time_warp/timeutils.py
photos_time_warp/timezones.py
photos_time_warp/utils.py
photos_time_warp-0.1.4.dist-info/LICENSE
photos_time_warp-0.1.4.dist-info/METADATA
photos_time_warp-0.1.4.dist-info/WHEEL
photos_time_warp-0.1.4.dist-info/entry_points.txt
photos_time_warp-0.1.4.dist-info/top_level.txt
photos_time_warp-0.1.4.dist-info/RECORD
