Metadata-Version: 2.1
Name: photos-time-warp
Version: 0.1.4
Summary: Adjust date and/or time of photos in Apple Photos
Home-page: https://github.com/RhetTbull/exif2findertags
Author: Rhet Turnbull
Author-email: rturnbull+git@gmail.com
License: License :: OSI Approved :: MIT License
Download-URL: https://github.com/RhetTbull/exif2findertags
Project-URL: GitHub, https://github.com/RhetTbull/exif2findertags
Platform: UNKNOWN
Classifier: Development Status :: 4 - Beta
Classifier: Environment :: MacOS X
Classifier: License :: OSI Approved :: MIT License
Classifier: Intended Audience :: End Users/Desktop
Classifier: Operating System :: MacOS :: MacOS X
Classifier: Programming Language :: Python :: 3.7
Classifier: Programming Language :: Python :: 3.8
Classifier: Programming Language :: Python :: 3.9
Classifier: Topic :: Software Development :: Libraries :: Python Modules
Requires-Python: >=3.7
License-File: LICENSE
Requires-Dist: osxphotos (<0.43.0,>=0.42.82)
Requires-Dist: click (<9.0.0,==8.0.1)
Requires-Dist: cloup (<0.12.0,>=0.11.0)
Requires-Dist: rich (<11.0.0,>=10.6.0)
Requires-Dist: pytimeparse (<1.2.0,>=1.1.8)
Requires-Dist: photoscript (<0.2.0,>=0.1.4)
Requires-Dist: pyobjc-core (<8.0,>=7.3)
Requires-Dist: tenacity (<9.0.0,>=8.0.1)
